[{"model": "monitor.host", "pk": 1, "fields": {"name": "localhost", "description": "", "ipv4": "0.0.0.0", "last_check": "2022-04-26T13:47:13.758Z", "last_status_change": "2019-04-08T12:21:40.486Z", "status_info": "Connected", "status": 1}}, {"model": "monitor.host", "pk": 3, "fields": {"name": "OpenDNS External DNS", "description": "", "ipv4": "208.67.222.222", "last_check": "2022-04-26T13:47:14.775Z", "last_status_change": "2019-04-08T12:24:03.196Z", "status_info": "Connected", "status": 1}}, {"model": "monitor.host", "pk": 4, "fields": {"name": "Cloudflare18 external dns", "description": "", "ipv4": "1.1.1.1", "last_check": "2022-04-26T13:47:12.717Z", "last_status_change": "2019-04-08T12:24:38.049Z", "status_info": "Connected", "status": 1}}]